pisco_segmenter/.gitkeep
pisco_segmenter/bg_correction.py
pisco_segmenter-0.1.0.dist-info/METADATA
pisco_segmenter-0.1.0.dist-info/WHEEL
pisco_segmenter-0.1.0.dist-info/RECORD
