Metadata-Version: 2.1
Name: pisco-segmenter
Version: 0.1.0
Summary: image processing and segmentation for pisco plankton imaging system
License: MIT
Author: Veit Dausmann & Tim Kalsberger
Author-email: vdausmann@geomar.de
Requires-Python: >=3.10,<4.0
Classifier: License :: OSI Approved :: MIT License
Classifier: Programming Language :: Python :: 3
Classifier: Programming Language :: Python :: 3.10
Classifier: Programming Language :: Python :: 3.11
Requires-Dist: numpy (>=1.25.1,<2.0.0)
Requires-Dist: opencv-python (>=4.8.0.74,<5.0.0.0)
Requires-Dist: torch (>=2.0.1,<3.0.0)
